ferda_time_translator/__init__.py
ferda_time_translator/constants.py
ferda_time_translator/translator.py
ferda_time_translator-0.1.3.dist-info/LICENSE
ferda_time_translator-0.1.3.dist-info/WHEEL
ferda_time_translator-0.1.3.dist-info/METADATA
ferda_time_translator-0.1.3.dist-info/RECORD
