Metadata-Version: 2.1
Name: ferda-time-translator
Version: 0.1.3
Summary: Simple program that will translate the current time into ferda standard time (FST)
License: MIT
Author: Will Lavalliere
Author-email: willlavalliere@gmail.com
Requires-Python: >=3.9,<4.0
Classifier: License :: OSI Approved :: MIT License
Classifier: Programming Language :: Python :: 3
Classifier: Programming Language :: Python :: 3.10
Classifier: Programming Language :: Python :: 3.9
